{
	"configurations" : 
	[
		{
			"directories" : 
			[
				{
					"build" : ".",
					"jsonFile" : "directory-.-Debug-d0094a50bb2071803777.json",
					"minimumCMakeVersion" : 
					{
						"string" : "3.24"
					},
					"projectIndex" : 0,
					"source" : ".",
					"targetIndexes" : 
					[
						0
					]
				}
			],
			"name" : "Debug",
			"projects" : 
			[
				{
					"directoryIndexes" : 
					[
						0
					],
					"name" : "PriorityQueue",
					"targetIndexes" : 
					[
						0
					]
				}
			],
			"targets" : 
			[
				{
					"directoryIndex" : 0,
					"id" : "PriorityQueue::@6890427a1f51a3e7e1df",
					"jsonFile" : "target-PriorityQueue-Debug-abf671b1aaa8122e90f1.json",
					"name" : "PriorityQueue",
					"projectIndex" : 0
				}
			]
		}
	],
	"kind" : "codemodel",
	"paths" : 
	{
		"build" : "C:/Users/Andreea Bacea/Desktop/anul I/anul I sem II/DSA/PriorityQueue/cmake-build-debug",
		"source" : "C:/Users/Andreea Bacea/Desktop/anul I/anul I sem II/DSA/PriorityQueue"
	},
	"version" : 
	{
		"major" : 2,
		"minor" : 4
	}
}
